{
  "results": [
    {
      "id": "serial-21857",
      "type": "anime-serial",
      "link": "",
      "title": "Воины-марионетки Эр",
      "title_orig": "SM Girls: Saber Marionette R",
      "other_title": "Saber Marionette R",
      "translation": {
        "id": 827,
        "title": "Persona99",
        "type": "voice"
      },
      "year": 1995,
      "last_season": 1,
      "last_episode": 3,
      "episodes_count": 3,
      "kinopoisk_id": "821006",
      "imdb_id": "tt3422000",
      "worldart_link": "http://www.world-art.ru/animation/animation.php?id=2986",
      "shikimori_id": "1232",
      "quality": "DVDRip",
      "camrip": false,
      "blocked_countries": [],
      "blocked_seasons": {},
      "created_at": "2020-01-28T10:57:53Z",
      "updated_at": "2020-01-28T10:59:01Z"
    },
    {
      "id": "serial-21856",
      "type": "anime-serial",
      "link": "",
      "title": "Югио! Дуэльные монстры",
      "title_orig": "Yuu Gi Ou: Duel Monsters",
      "other_title": "Ю-Ги-О! Дуэльные Монстры / Югио: Дуэльные монстры",
      "translation": {
        "id": 674,
        "title": "Люб. Одноголосый",
        "type": "voice"
      },
      "year": 2000,
      "last_season": 2,
      "last_episode": 224,
      "episodes_count": 224,
      "kinopoisk_id": "230088",
      "imdb_id": "tt0247902",
      "worldart_link": "http://www.world-art.ru/animation/animation.php?id=3507",
      "shikimori_id": "481",
      "quality": "DVDRip",
      "camrip": false,
      "blocked_countries": [],
      "blocked_seasons": {},
      "created_at": "2020-01-28T10:47:29Z",
      "updated_at": "2020-01-28T10:50:49Z"
    },
    {
      "id": "serial-21853",
      "type": "anime-serial",
      "link": "",
      "title": "Кизнайвер",
      "title_orig": "Kiznaiver",
      "other_title": "Связанные",
      "translation": {
        "id": 767,
        "title": "SHIZA Project",
        "type": "voice"
      },
      "year": 2016,
      "last_season": 1,
      "last_episode": 12,
      "episodes_count": 12,
      "kinopoisk_id": "977712",
      "imdb_id": "tt5225712",
      "worldart_link": "http://www.world-art.ru/animation/animation.php?id=8505",
      "shikimori_id": "31798",
      "quality": "HDTVRip 720p",
      "camrip": false,
      "blocked_countries": [],
      "blocked_seasons": {},
      "created_at": "2020-01-28T10:23:30Z",
      "updated_at": "2020-01-28T10:23:30Z"
    },
    {
      "id": "serial-21852",
      "type": "anime-serial",
      "link": "",
      "title": "Усио и Тора [ТВ-2]",
      "title_orig": "Ushio to Tora",
      "other_title": "Ушио и Тора 2",
      "translation": {
        "id": 767,
        "title": "SHIZA Project",
        "type": "voice"
      },
      "year": 2016,
      "last_season": 2,
      "last_episode": 13,
      "episodes_count": 13,
      "kinopoisk_id": "917919",
      "imdb_id": "tt4801510",
      "worldart_link": "http://www.world-art.ru/animation/animation.php?id=8373",
      "shikimori_id": "31098",
      "quality": "HDTVRip 720p",
      "camrip": false,
      "blocked_countries": [],
      "blocked_seasons": {},
      "created_at": "2020-01-28T09:55:03Z",
      "updated_at": "2020-01-28T09:55:03Z"
    },
    {
      "id": "serial-8309",
      "type": "anime-serial",
      "link": "",
      "title": "Великий из бродячих псов [ТВ-1]",
      "title_orig": "Bungou Stray Dogs",
      "other_title": "Бродячие псы / Бродячие псы литературы [ТВ-1] / Проза бродячих псов",
      "translation": {
        "id": 767,
        "title": "SHIZA Project",
        "type": "voice"
      },
      "year": 2016,
      "last_season": 1,
      "last_episode": 12,
      "episodes_count": 12,
      "kinopoisk_id": "975895",
      "imdb_id": "tt5679720",
      "worldart_link": "http://www.world-art.ru/animation/animation.php?id=8406",
      "shikimori_id": "31478",
      "quality": "HDTVRip 720p",
      "camrip": false,
      "blocked_countries": [],
      "blocked_seasons": {},
      "created_at": "2018-01-04T05:15:33Z",
      "updated_at": "2020-01-28T09:49:19Z"
    },
    {
      "id": "serial-21851",
      "type": "anime-serial",
      "link": "",
      "title": "Апельсин",
      "title_orig": "Orange",
      "other_title": "Орендж",
      "translation": {
        "id": 767,
        "title": "SHIZA Project",
        "type": "voice"
      },
      "year": 2016,
      "last_season": 1,
      "last_episode": 13,
      "episodes_count": 13,
      "kinopoisk_id": "1003934",
      "imdb_id": "tt5839732",
      "worldart_link": "http://www.world-art.ru/animation/animation.php?id=8680",
      "shikimori_id": "32729",
      "quality": "HDTVRip 720p",
      "camrip": false,
      "blocked_countries": [],
      "blocked_seasons": {},
      "created_at": "2020-01-28T09:47:54Z",
      "updated_at": "2020-01-28T09:47:54Z"
    },
    {
      "id": "serial-21850",
      "type": "anime-serial",
      "link": "",
      "title": "Чёрная сталь",
      "title_orig": "Kuromukuro",
      "other_title": "Черный хром",
      "translation": {
        "id": 767,
        "title": "SHIZA Project",
        "type": "voice"
      },
      "year": 2016,
      "last_season": 1,
      "last_episode": 26,
      "episodes_count": 26,
      "kinopoisk_id": "1009684",
      "imdb_id": "tt5895314",
      "worldart_link": "http://www.world-art.ru/animation/animation.php?id=8619",
      "shikimori_id": "32245",
      "quality": "HDTVRip 720p",
      "camrip": false,
      "blocked_countries": [],
      "blocked_seasons": {},
      "created_at": "2020-01-28T09:36:58Z",
      "updated_at": "2020-01-28T09:36:58Z"
    },
    {
      "id": "serial-21849",
      "type": "anime-serial",
      "link": "",
      "title": "Сотня",
      "title_orig": "Hundred",
      "other_title": "СотЭнчик",
      "translation": {
        "id": 767,
        "title": "SHIZA Project",
        "type": "voice"
      },
      "year": 2016,
      "last_season": 1,
      "last_episode": 12,
      "episodes_count": 12,
      "kinopoisk_id": "987687",
      "imdb_id": "tt5271506",
      "worldart_link": "http://www.world-art.ru/animation/animation.php?id=8599",
      "shikimori_id": "31338",
      "quality": "HDTVRip 720p",
      "camrip": false,
      "blocked_countries": [],
      "blocked_seasons": {},
      "created_at": "2020-01-28T09:30:49Z",
      "updated_at": "2020-01-28T09:30:49Z"
    },
    {
      "id": "serial-8382",
      "type": "anime-serial",
      "link": "",
      "title": "Дни [ТВ]",
      "title_orig": "Days",
      "translation": {
        "id": 767,
        "title": "SHIZA Project",
        "type": "voice"
      },
      "year": 2016,
      "last_season": 1,
      "last_episode": 24,
      "episodes_count": 24,
      "kinopoisk_id": "1111820",
      "imdb_id": "tt5897818",
      "worldart_link": "http://www.world-art.ru/animation/animation.php?id=8637",
      "shikimori_id": "32494",
      "quality": "WEB-DLRip 720p",
      "camrip": false,
      "blocked_countries": [],
      "blocked_seasons": {},
      "created_at": "2018-01-05T03:46:49Z",
      "updated_at": "2020-01-28T09:28:32Z"
    },
    {
      "id": "serial-21848",
      "type": "anime-serial",
      "link": "",
      "title": "Моб Психо 100 [ТВ-1]",
      "title_orig": "Mob Psycho 100",
      "other_title": "モブサイコ100",
      "translation": {
        "id": 767,
        "title": "SHIZA Project",
        "type": "voice"
      },
      "year": 2016,
      "last_season": 1,
      "last_episode": 12,
      "episodes_count": 12,
      "kinopoisk_id": "1002686",
      "imdb_id": "tt5897304",
      "worldart_link": "http://www.world-art.ru/animation/animation.php?id=8586",
      "shikimori_id": "32182",
      "quality": "BDRip 720p",
      "camrip": false,
      "blocked_countries": [],
      "blocked_seasons": {},
      "created_at": "2020-01-28T09:25:28Z",
      "updated_at": "2020-01-28T09:25:28Z"
    },
    {
      "id": "serial-21847",
      "type": "anime-serial",
      "link": "",
      "title": "Моя геройская академия [ТВ-2]",
      "title_orig": "Boku no Hero Academia 2",
      "other_title": "My Hero Academia Season 2",
      "translation": {
        "id": 559,
        "title": "Kansai",
        "type": "voice"
      },
      "year": 2016,
      "last_season": 2,
      "last_episode": 25,
      "episodes_count": 25,
      "kinopoisk_id": "975897",
      "imdb_id": "tt5626028",
      "worldart_link": "http://www.world-art.ru/animation/animation.php?id=8837",
      "shikimori_id": "33486",
      "quality": "WEB-DLRip 720p",
      "camrip": false,
      "blocked_countries": [],
      "blocked_seasons": {},
      "created_at": "2020-01-28T09:17:50Z",
      "updated_at": "2020-01-28T09:17:50Z"
    },
    {
      "id": "serial-21846",
      "type": "anime-serial",
      "link": "",
      "title": "Моя геройская академия [ТВ-1]",
      "title_orig": "Boku no Hero Academia",
      "other_title": "My Hero Academia",
      "translation": {
        "id": 767,
        "title": "SHIZA Project",
        "type": "voice"
      },
      "year": 2016,
      "last_season": 1,
      "last_episode": 13,
      "episodes_count": 13,
      "kinopoisk_id": "975897",
      "imdb_id": "tt5626028",
      "worldart_link": "http://www.world-art.ru/animation/animation.php?id=8530",
      "shikimori_id": "31964",
      "quality": "HDTVRip 720p",
      "camrip": false,
      "blocked_countries": [],
      "blocked_seasons": {},
      "created_at": "2020-01-28T09:14:21Z",
      "updated_at": "2020-01-28T09:14:21Z"
    },
    {
      "id": "serial-8292",
      "type": "anime-serial",
      "link": "",
      "title": "Берсерк [ТВ-3]",
      "title_orig": "Berserk (2017)",
      "other_title": "Beruseruku",
      "translation": {
        "id": 767,
        "title": "SHIZA Project",
        "type": "voice"
      },
      "year": 2017,
      "last_season": 3,
      "last_episode": 13,
      "episodes_count": 13,
      "kinopoisk_id": "991695",
      "imdb_id": "tt5847454",
      "worldart_link": "http://www.world-art.ru/animation/animation.php?id=8932",
      "shikimori_id": "34055",
      "quality": "WEB-DLRip 720p",
      "camrip": false,
      "blocked_countries": [],
      "blocked_seasons": {},
      "created_at": "2018-01-04T02:46:46Z",
      "updated_at": "2020-01-28T09:10:41Z"
    },
    {
      "id": "serial-21844",
      "type": "anime-serial",
      "link": "",
      "title": "Тайные желания отвергнутых",
      "title_orig": "Kuzu no honkai",
      "other_title": "Грязные желания / Scum's Wish",
      "translation": {
        "id": 767,
        "title": "SHIZA Project",
        "type": "voice"
      },
      "year": 2017,
      "last_season": 1,
      "last_episode": 12,
      "episodes_count": 12,
      "kinopoisk_id": "1008394",
      "imdb_id": "tt6197170",
      "worldart_link": "http://www.world-art.ru/animation/animation.php?id=8702",
      "shikimori_id": "32949",
      "quality": "BDRip 720p",
      "camrip": false,
      "blocked_countries": [],
      "blocked_seasons": {},
      "created_at": "2020-01-28T08:31:58Z",
      "updated_at": "2020-01-28T08:31:58Z"
    },
    {
      "id": "serial-5188",
      "type": "anime-serial",
      "link": "",
      "title": "Кулинарные поединки Сомы [ТВ-3, сезон 1]",
      "title_orig": "Shokugeki no Souma: San no Sara",
      "other_title": "В поисках божественного рецепта / Повар-боец Сома - Третье блюдо / Food Wars! The Third Plate",
      "translation": {
        "id": 767,
        "title": "SHIZA Project",
        "type": "voice"
      },
      "year": 2017,
      "last_season": 3,
      "last_episode": 12,
      "episodes_count": 12,
      "kinopoisk_id": "917288",
      "imdb_id": "tt4731072",
      "worldart_link": "http://www.world-art.ru/animation/animation.php?id=9295",
      "shikimori_id": "35788",
      "quality": "BDRip 720p",
      "camrip": false,
      "blocked_countries": [],
      "blocked_seasons": {},
      "created_at": "2017-10-28T11:12:00Z",
      "updated_at": "2020-01-28T08:24:11Z"
    },
    {
      "id": "serial-21843",
      "type": "anime-serial",
      "link": "",
      "title": "Кулинарные поединки Сомы [ТВ-2]",
      "title_orig": "Shokugeki no Souma: Ni no Sara",
      "other_title": "В поисках божественного рецепта / Кулинарные Поединки Сомы: Второе Блюдо [ТВ-2] / Повар-боец Сома (2 сезон)",
      "translation": {
        "id": 767,
        "title": "SHIZA Project",
        "type": "voice"
      },
      "year": 2016,
      "last_season": 2,
      "last_episode": 13,
      "episodes_count": 13,
      "kinopoisk_id": "917288",
      "imdb_id": "tt4731072",
      "worldart_link": "http://www.world-art.ru/animation/animation.php?id=8598",
      "shikimori_id": "32282",
      "quality": "BDRip 720p",
      "camrip": false,
      "blocked_countries": [],
      "blocked_seasons": {},
      "created_at": "2020-01-28T08:22:00Z",
      "updated_at": "2020-01-28T08:22:00Z"
    },
    {
      "id": "serial-21842",
      "type": "anime-serial",
      "link": "",
      "title": "Гинтама [ТВ-7]",
      "title_orig": "Gintama. (2018)",
      "other_title": "Гинтама 7 / Gintama.: Shirogane no Tamashii-hen",
      "translation": {
        "id": 767,
        "title": "SHIZA Project",
        "type": "voice"
      },
      "year": 2018,
      "last_season": 7,
      "last_episode": 12,
      "episodes_count": 12,
      "kinopoisk_id": "490128",
      "imdb_id": "tt0988818",
      "worldart_link": "http://www.world-art.ru/animation/animation.php?id=9625",
      "shikimori_id": "36838",
      "quality": "WEB-DLRip 720p",
      "camrip": false,
      "blocked_countries": [],
      "blocked_seasons": {},
      "created_at": "2020-01-28T08:15:16Z",
      "updated_at": "2020-01-28T08:15:16Z"
    },
    {
      "id": "serial-21841",
      "type": "anime-serial",
      "link": "",
      "title": "Гинтама [ТВ-6]",
      "title_orig": "Gintama Season 4 (2017)",
      "other_title": "Гинтама 6 / Gintama.: Porori-hen",
      "translation": {
        "id": 767,
        "title": "SHIZA Project",
        "type": "voice"
      },
      "year": 2017,
      "last_season": 6,
      "last_episode": 13,
      "episodes_count": 13,
      "kinopoisk_id": "490128",
      "imdb_id": "tt0988818",
      "worldart_link": "http://www.world-art.ru/animation/animation.php?id=9315",
      "shikimori_id": "35843",
      "quality": "WEB-DLRip 720p",
      "camrip": false,
      "blocked_countries": [],
      "blocked_seasons": {},
      "created_at": "2020-01-28T08:11:17Z",
      "updated_at": "2020-01-28T08:11:17Z"
    },
    {
      "id": "serial-21840",
      "type": "anime-serial",
      "link": "",
      "title": "Золотое божество [ТВ-2]",
      "title_orig": "Golden Kamuy (2018)",
      "other_title": "Золотое Божество 2",
      "translation": {
        "id": 767,
        "title": "SHIZA Project",
        "type": "voice"
      },
      "year": 2018,
      "last_season": 2,
      "last_episode": 12,
      "episodes_count": 12,
      "kinopoisk_id": "1161904",
      "imdb_id": "tt8225204",
      "worldart_link": "http://www.world-art.ru/animation/animation.php?id=9744",
      "shikimori_id": "37989",
      "quality": "BDRip 720p",
      "camrip": false,
      "blocked_countries": [],
      "blocked_seasons": {},
      "created_at": "2020-01-28T08:08:01Z",
      "updated_at": "2020-01-28T08:08:01Z"
    },
    {
      "id": "serial-21839",
      "type": "anime-serial",
      "link": "",
      "title": "Дороро [ТВ-2]",
      "title_orig": "Dororo",
      "other_title": "どろろ",
      "translation": {
        "id": 767,
        "title": "SHIZA Project",
        "type": "voice"
      },
      "year": 2019,
      "last_season": 2,
      "last_episode": 24,
      "episodes_count": 24,
      "kinopoisk_id": "1226631",
      "imdb_id": "tt9458304",
      "worldart_link": "http://www.world-art.ru/animation/animation.php?id=9635",
      "shikimori_id": "37520",
      "quality": "WEB-DLRip 720p",
      "camrip": false,
      "blocked_countries": [],
      "blocked_seasons": {},
      "created_at": "2020-01-28T08:03:36Z",
      "updated_at": "2020-01-28T08:03:36Z"
    },
    {
      "id": "serial-21838",
      "type": "anime-serial",
      "link": "",
      "title": "Озорная Такаги [ТВ-2]",
      "title_orig": "Karakai Jouzu no Takagi-san 2",
      "other_title": "Озорная Такаги 2 / Шутница Такаги / Мастер дразнилок Такаги",
      "translation": {
        "id": 767,
        "title": "SHIZA Project",
        "type": "voice"
      },
      "year": 2019,
      "last_season": 2,
      "last_episode": 12,
      "episodes_count": 12,
      "kinopoisk_id": "1115564",
      "imdb_id": "tt7808344",
      "worldart_link": "http://www.world-art.ru/animation/animation.php?id=9953",
      "shikimori_id": "38993",
      "quality": "WEB-DLRip 720p",
      "camrip": false,
      "blocked_countries": [],
      "blocked_seasons": {},
      "created_at": "2020-01-28T08:00:05Z",
      "updated_at": "2020-01-28T08:00:05Z"
    },
    {
      "id": "serial-21837",
      "type": "anime-serial",
      "link": "",
      "title": "Бэм",
      "title_orig": "Bem",
      "translation": {
        "id": 767,
        "title": "SHIZA Project",
        "type": "voice"
      },
      "year": 2019,
      "last_season": 1,
      "last_episode": 12,
      "episodes_count": 12,
      "kinopoisk_id": "1271349",
      "imdb_id": "tt10423424",
      "worldart_link": "http://www.world-art.ru/animation/animation.php?id=9980",
      "shikimori_id": "39221",
      "quality": "WEB-DLRip 720p",
      "camrip": false,
      "blocked_countries": [],
      "blocked_seasons": {},
      "created_at": "2020-01-28T07:57:28Z",
      "updated_at": "2020-01-28T07:57:28Z"
    },
    {
      "id": "movie-48376",
      "type": "foreign-movie",
      "link": "",
      "title": "Гангстер-шаман",
      "title_orig": "Bak-su-geon-dal",
      "translation": {
        "id": 613,
        "title": "DeadSno & den904",
        "type": "voice"
      },
      "year": 2013,
      "kinopoisk_id": "731176",
      "imdb_id": "tt2630028",
      "quality": "HDRip",
      "camrip": false,
      "blocked_countries": [],
      "created_at": "2020-01-27T21:40:12Z",
      "updated_at": "2020-01-27T21:40:12Z"
    },
    {
      "id": "movie-48373",
      "type": "anime",
      "link": "",
      "title": "Проблемные дети из другого мира OVA",
      "title_orig": "Mondaiji OVA",
      "other_title": "Проблемные дети из другого мира",
      "translation": {
        "id": 767,
        "title": "SHIZA Project",
        "type": "voice"
      },
      "year": 2013,
      "worldart_link": "http://www.world-art.ru/animation/animation.php?id=1263",
      "shikimori_id": "16444",
      "quality": "BDRip 720p",
      "camrip": false,
      "blocked_countries": [],
      "created_at": "2020-01-27T21:36:37Z",
      "updated_at": "2020-01-27T21:36:37Z"
    },
    {
      "id": "serial-21829",
      "type": "anime-serial",
      "link": "",
      "title": "Класс убийц [ТВ-2]",
      "title_orig": "Ansatsu Kyoushitsu: Second Season",
      "other_title": "Класс убийц 2 / Класс Убийц 2",
      "translation": {
        "id": 767,
        "title": "SHIZA Project",
        "type": "voice"
      },
      "year": 2016,
      "last_season": 2,
      "last_episode": 25,
      "episodes_count": 25,
      "kinopoisk_id": "880618",
      "imdb_id": "tt3837246",
      "worldart_link": "http://www.world-art.ru/animation/animation.php?id=8477",
      "shikimori_id": "30654",
      "quality": "HDTVRip 720p",
      "camrip": false,
      "blocked_countries": [],
      "blocked_seasons": {},
      "created_at": "2020-01-27T21:34:12Z",
      "updated_at": "2020-01-27T21:34:12Z"
    },
    {
      "id": "serial-21828",
      "type": "anime-serial",
      "link": "",
      "title": "Мужичок и Зефирка",
      "title_orig": "Ojisan to Marshmallow",
      "other_title": "Дядька и зефирки / Дядя и зефир",
      "translation": {
        "id": 767,
        "title": "SHIZA Project",
        "type": "voice"
      },
      "year": 2016,
      "last_season": 1,
      "last_episode": 12,
      "episodes_count": 13,
      "kinopoisk_id": "1378836",
      "imdb_id": "tt5461834",
      "worldart_link": "http://www.world-art.ru/animation/animation.php?id=8542",
      "shikimori_id": "31848",
      "quality": "BDRip 720p",
      "camrip": false,
      "blocked_countries": [],
      "blocked_seasons": {},
      "created_at": "2020-01-27T21:30:16Z",
      "updated_at": "2020-01-27T21:30:16Z"
    },
    {
      "id": "movie-48372",
      "type": "anime",
      "link": "",
      "title": "Академия ведьмочек: Колдовской парад",
      "title_orig": "Ritoru wicchi akademia: Mahoujihikake no parêdo",
      "other_title": "Академия ведьмочек 2 / Академия ведьмочек (фильм второй) / Академия ведьмочек: Волшебный парад / Little Witch Academia: Mahoujikake no Parade",
      "translation": {
        "id": 767,
        "title": "SHIZA Project",
        "type": "voice"
      },
      "year": 2015,
      "kinopoisk_id": "921018",
      "imdb_id": "tt4831682",
      "worldart_link": "http://www.world-art.ru/animation/animation.php?id=1758",
      "shikimori_id": "19489",
      "quality": "BDRip 720p",
      "camrip": false,
      "blocked_countries": [],
      "created_at": "2020-01-27T21:26:43Z",
      "updated_at": "2020-01-27T21:26:43Z"
    },
    {
      "id": "movie-48371",
      "type": "anime",
      "link": "",
      "title": "Не моя вина, что я не популярна! OVA",
      "title_orig": "Watashi ga Motenai no wa Dou Kangaete mo Omaera ga Warui!: Motenai shi, Nazo Meite Miru",
      "other_title": "Это всё ваша вина, что я не популярна!",
      "translation": {
        "id": 767,
        "title": "SHIZA Project",
        "type": "voice"
      },
      "year": 2014,
      "worldart_link": "http://www.world-art.ru/animation/animation.php?id=1744",
      "shikimori_id": "20449",
      "quality": "DVDRip",
      "camrip": false,
      "blocked_countries": [],
      "created_at": "2020-01-27T21:24:37Z",
      "updated_at": "2020-01-27T21:24:37Z"
    },
    {
      "id": "movie-48370",
      "type": "anime",
      "link": "",
      "title": "Женская логика OVA",
      "title_orig": "Joshiraku (2013)",
      "other_title": "В ракуго только девушки",
      "translation": {
        "id": 767,
        "title": "SHIZA Project",
        "type": "voice"
      },
      "year": 2013,
      "worldart_link": "http://www.world-art.ru/animation/animation.php?id=5635",
      "shikimori_id": "15591",
      "quality": "DVDRip",
      "camrip": false,
      "blocked_countries": [],
      "created_at": "2020-01-27T21:23:37Z",
      "updated_at": "2020-01-27T21:23:37Z"
    },
    {
      "id": "serial-21827",
      "type": "anime-serial",
      "link": "",
      "title": "Запретная татуировка",
      "title_orig": "Taboo-Tattoo",
      "other_title": "タブー・タトゥー",
      "translation": {
        "id": 767,
        "title": "SHIZA Project",
        "type": "voice"
      },
      "year": 2016,
      "last_season": 1,
      "last_episode": 12,
      "episodes_count": 12,
      "kinopoisk_id": "1004218",
      "imdb_id": "tt5679248",
      "worldart_link": "http://www.world-art.ru/animation/animation.php?id=8725",
      "shikimori_id": "29758",
      "quality": "HDTVRip 720p",
      "camrip": false,
      "blocked_countries": [],
      "blocked_seasons": {},
      "created_at": "2020-01-27T21:22:37Z",
      "updated_at": "2020-01-27T21:22:37Z"
    },
    {
      "id": "serial-19454",
      "type": "anime-serial",
      "link": "",
      "title": "Вавилон",
      "title_orig": "Babylon",
      "other_title": "バビロン",
      "translation": {
        "id": 910,
        "title": "AniStar",
        "type": "voice"
      },
      "year": 2019,
      "last_season": 1,
      "last_episode": 12,
      "episodes_count": 12,
      "kinopoisk_id": "1306615",
      "imdb_id": "tt10937632",
      "worldart_link": "http://www.world-art.ru/animation/animation.php?id=9637",
      "shikimori_id": "37525",
      "quality": "HDTVRip 720p",
      "camrip": false,
      "blocked_countries": [],
      "blocked_seasons": {},
      "created_at": "2019-10-28T17:29:46Z",
      "updated_at": "2020-01-27T15:22:36Z"
    },
    {
      "id": "movie-48359",
      "type": "anime",
      "link": "",
      "title": "Звёздный герб OVA",
      "title_orig": "Seikai no Danshou: Tanjou",
      "other_title": "Crest of the Stars: Birth",
      "translation": {
        "id": 767,
        "title": "SHIZA Project",
        "type": "voice"
      },
      "year": 2000,
      "worldart_link": "http://www.world-art.ru/animation/animation.php?id=3113",
      "shikimori_id": "1124",
      "quality": "DVDRip",
      "camrip": false,
      "blocked_countries": [],
      "created_at": "2020-01-27T15:19:09Z",
      "updated_at": "2020-01-27T15:19:09Z"
    },
    {
      "id": "movie-48358",
      "type": "anime",
      "link": "",
      "title": "Письмо для Момо",
      "title_orig": "Momo e no tegami",
      "other_title": "A Letter to Momo",
      "translation": {
        "id": 767,
        "title": "SHIZA Project",
        "type": "voice"
      },
      "year": 2011,
      "kinopoisk_id": "635011",
      "imdb_id": "tt1853614",
      "worldart_link": "http://www.world-art.ru/animation/animation.php?id=794",
      "shikimori_id": "10389",
      "quality": "BDRip 720p",
      "camrip": false,
      "blocked_countries": [],
      "created_at": "2020-01-27T15:17:40Z",
      "updated_at": "2020-01-27T15:17:40Z"
    },
    {
      "id": "movie-48357",
      "type": "anime",
      "link": "",
      "title": "Хряк",
      "title_orig": "Buta",
      "translation": {
        "id": 767,
        "title": "SHIZA Project",
        "type": "voice"
      },
      "year": 2012,
      "kinopoisk_id": "707285",
      "imdb_id": "tt7098070",
      "worldart_link": "http://www.world-art.ru/animation/animation.php?id=1020",
      "shikimori_id": "13169",
      "quality": "HDTVRip 720p",
      "camrip": false,
      "blocked_countries": [],
      "created_at": "2020-01-27T15:16:52Z",
      "updated_at": "2020-01-27T15:16:52Z"
    },
    {
      "id": "movie-48356",
      "type": "anime",
      "link": "",
      "title": "Призрак в доспехах: Синдром одиночки – Одиннадцать индивидуалистов",
      "title_orig": "Kôkaku kidôtai: S.A.C. 2nd GIG - Individual eleven",
      "other_title": "Призрак в доспехах: Синдром одиночки (компиляция #2)",
      "translation": {
        "id": 767,
        "title": "SHIZA Project",
        "type": "voice"
      },
      "year": 2006,
      "kinopoisk_id": "317169",
      "imdb_id": "tt1024214",
      "worldart_link": "http://www.world-art.ru/animation/animation.php?id=5691",
      "shikimori_id": "2448",
      "quality": "DVDRip",
      "camrip": false,
      "blocked_countries": [],
      "created_at": "2020-01-27T15:15:59Z",
      "updated_at": "2020-01-27T15:15:59Z"
    },
    {
      "id": "movie-48355",
      "type": "anime",
      "link": "",
      "title": "Невеста Деймоса: Улыбка орхидеи",
      "title_orig": "Deimos no Hanayome: Ran no Kumikyoku",
      "other_title": "Невеста Деймоса - Улыбка орхидеи",
      "translation": {
        "id": 767,
        "title": "SHIZA Project",
        "type": "voice"
      },
      "year": 1988,
      "kinopoisk_id": "708402",
      "imdb_id": "tt6102406",
      "worldart_link": "http://www.world-art.ru/animation/animation.php?id=446",
      "shikimori_id": "5918",
      "quality": "VHSRip",
      "camrip": false,
      "blocked_countries": [],
      "created_at": "2020-01-27T14:43:54Z",
      "updated_at": "2020-01-27T14:43:54Z"
    },
    {
      "id": "movie-48354",
      "type": "anime",
      "link": "",
      "title": "Соприкоснувшиеся миры",
      "title_orig": "Meguriau Sekai",
      "other_title": "World Comes Around",
      "translation": {
        "id": 767,
        "title": "SHIZA Project",
        "type": "voice"
      },
      "year": 2009,
      "kinopoisk_id": "708895",
      "worldart_link": "http://www.world-art.ru/animation/animation.php?id=7817",
      "quality": "DVDRip",
      "camrip": false,
      "blocked_countries": [],
      "created_at": "2020-01-27T14:42:43Z",
      "updated_at": "2020-01-27T14:42:43Z"
    },
    {
      "id": "serial-21817",
      "type": "anime-serial",
      "link": "",
      "title": "Нодамэ Кантабиле OVA",
      "title_orig": "Nodame Cantabile OVA",
      "other_title": "のだめカンタービレ OVA",
      "translation": {
        "id": 767,
        "title": "SHIZA Project",
        "type": "voice"
      },
      "year": 2007,
      "last_season": 1,
      "last_episode": 2,
      "episodes_count": 2,
      "kinopoisk_id": "408694",
      "imdb_id": "tt0928099",
      "worldart_link": "http://www.world-art.ru/animation/animation.php?id=7426",
      "shikimori_id": "6187",
      "quality": "DVDRip",
      "camrip": false,
      "blocked_countries": [],
      "blocked_seasons": {},
      "created_at": "2020-01-27T14:41:30Z",
      "updated_at": "2020-01-27T14:41:30Z"
    },
    {
      "id": "serial-21816",
      "type": "anime-serial",
      "link": "",
      "title": "Ко всем чертям!",
      "title_orig": "Goddamn",
      "other_title": "ガッデム",
      "translation": {
        "id": 767,
        "title": "SHIZA Project",
        "type": "voice"
      },
      "year": 1990,
      "last_season": 1,
      "last_episode": 2,
      "episodes_count": 2,
      "kinopoisk_id": "1223873",
      "imdb_id": "tt4297116",
      "worldart_link": "http://www.world-art.ru/animation/animation.php?id=5031",
      "shikimori_id": "9646",
      "quality": "DVDRip",
      "camrip": false,
      "blocked_countries": [],
      "blocked_seasons": {},
      "created_at": "2020-01-27T14:39:44Z",
      "updated_at": "2020-01-27T14:39:44Z"
    },
    {
      "id": "serial-21815",
      "type": "anime-serial",
      "link": "",
      "title": "Навсегда мой Санта",
      "title_orig": "Itsudatte my Santa",
      "other_title": "Во веки мой санта\t/ Навсегда Мой Санта!",
      "translation": {
        "id": 767,
        "title": "SHIZA Project",
        "type": "voice"
      },
      "year": 2005,
      "last_season": 1,
      "last_episode": 2,
      "episodes_count": 2,
      "kinopoisk_id": "443706",
      "imdb_id": "tt1183366",
      "worldart_link": "http://www.world-art.ru/animation/animation.php?id=4973",
      "shikimori_id": "588",
      "quality": "DVDRip",
      "camrip": false,
      "blocked_countries": [],
      "blocked_seasons": {},
      "created_at": "2020-01-27T14:38:17Z",
      "updated_at": "2020-01-27T14:38:17Z"
    },
    {
      "id": "movie-48353",
      "type": "anime",
      "link": "",
      "title": "У меня мало друзей OVA-1",
      "title_orig": "Boku wa Tomodachi ga Sukunai: Yaminabe wa Bishoujo ga Zannen na Nioi",
      "other_title": "У меня мало друзей: Эпизод 0",
      "translation": {
        "id": 767,
        "title": "SHIZA Project",
        "type": "voice"
      },
      "year": 2011,
      "kinopoisk_id": "707597",
      "worldart_link": "http://www.world-art.ru/animation/animation.php?id=2235",
      "shikimori_id": "10897",
      "quality": "DVDRip",
      "camrip": false,
      "blocked_countries": [],
      "created_at": "2020-01-27T14:36:19Z",
      "updated_at": "2020-01-27T14:36:19Z"
    },
    {
      "id": "movie-48352",
      "type": "anime",
      "link": "",
      "title": "Био-охотник",
      "title_orig": "Baio hantâ",
      "other_title": "Bio Hunter",
      "translation": {
        "id": 767,
        "title": "SHIZA Project",
        "type": "voice"
      },
      "year": 1995,
      "kinopoisk_id": "52335",
      "imdb_id": "tt0220333",
      "worldart_link": "http://www.world-art.ru/animation/animation.php?id=458",
      "shikimori_id": "1269",
      "quality": "DVDRip",
      "camrip": false,
      "blocked_countries": [],
      "created_at": "2020-01-27T14:34:46Z",
      "updated_at": "2020-01-27T14:34:46Z"
    },
    {
      "id": "serial-21814",
      "type": "anime-serial",
      "link": "",
      "title": "Флейта в рюкзаке OVA",
      "title_orig": "Recorder to Randsell OVA",
      "other_title": "Флейта и ранец / Флейта да ранец / Флейта и Ранец ОВА",
      "translation": {
        "id": 767,
        "title": "SHIZA Project",
        "type": "voice"
      },
      "year": 2012,
      "last_season": 1,
      "last_episode": 2,
      "episodes_count": 2,
      "kinopoisk_id": "714218",
      "worldart_link": "http://www.world-art.ru/animation/animation.php?id=1586",
      "shikimori_id": "14627",
      "quality": "DVDRip",
      "camrip": false,
      "blocked_countries": [],
      "blocked_seasons": {},
      "created_at": "2020-01-27T14:32:48Z",
      "updated_at": "2020-01-27T14:32:48Z"
    },
    {
      "id": "movie-48351",
      "type": "anime",
      "link": "",
      "title": "Шинки – боевой Лунный Ангел",
      "title_orig": "Busou Shinki Moon Angel",
      "other_title": "Busou Shinki: Moon Angel",
      "translation": {
        "id": 767,
        "title": "SHIZA Project",
        "type": "voice"
      },
      "year": 2011,
      "kinopoisk_id": "630308",
      "imdb_id": "tt2074341",
      "worldart_link": "http://www.world-art.ru/animation/animation.php?id=5380",
      "shikimori_id": "11103",
      "quality": "BDRip 720p",
      "camrip": false,
      "blocked_countries": [],
      "created_at": "2020-01-27T14:31:21Z",
      "updated_at": "2020-01-27T14:31:21Z"
    },
    {
      "id": "serial-8317",
      "type": "anime-serial",
      "link": "",
      "title": "Великолепный кондитер [ТВ-1]",
      "title_orig": "Yume-iro Patissiere",
      "other_title": "Yumeiro Patissiere",
      "translation": {
        "id": 767,
        "title": "SHIZA Project",
        "type": "voice"
      },
      "year": 2009,
      "last_season": 1,
      "last_episode": 50,
      "episodes_count": 50,
      "kinopoisk_id": "1046716",
      "imdb_id": "tt6608398",
      "worldart_link": "http://www.world-art.ru/animation/animation.php?id=7475",
      "shikimori_id": "6586",
      "quality": "HDTVRip",
      "camrip": false,
      "blocked_countries": [],
      "blocked_seasons": {},
      "created_at": "2018-01-04T05:34:29Z",
      "updated_at": "2020-01-27T14:28:46Z"
    },
    {
      "id": "movie-48349",
      "type": "anime",
      "link": "",
      "title": "Капитан Харлок: Тайна Аркадии",
      "title_orig": "Uchû kaizoku Captain Harlock: Arcadia-gô no nazo",
      "other_title": "Капитан Харлок - Тайна Аркадии / Captain Harlock: Mystery of the Arcadia / Uchuu Kaizoku Captain Harlock: Arcadia-gou no Nazo",
      "translation": {
        "id": 767,
        "title": "SHIZA Project",
        "type": "voice"
      },
      "year": 1978,
      "kinopoisk_id": "410363",
      "imdb_id": "tt0182646",
      "worldart_link": "http://www.world-art.ru/animation/animation.php?id=246",
      "shikimori_id": "2470",
      "quality": "BDRip 720p",
      "camrip": false,
      "blocked_countries": [],
      "created_at": "2020-01-27T14:26:30Z",
      "updated_at": "2020-01-27T14:26:30Z"
    },
    {
      "id": "movie-48348",
      "type": "anime",
      "link": "",
      "title": "Мобильный воин Зета Гандам: Новый перевод",
      "title_orig": "Kidô senshi Z Gandamu III: Hoshi no kodô wa ai",
      "other_title": "Мобильный воин Зета ГАНДАМ - Новый перевод (фильм третий)",
      "translation": {
        "id": 767,
        "title": "SHIZA Project",
        "type": "voice"
      },
      "year": 2006,
      "kinopoisk_id": "253186",
      "imdb_id": "tt0488584",
      "worldart_link": "http://www.world-art.ru/animation/animation.php?id=5415",
      "shikimori_id": "1969",
      "quality": "BDRip 720p",
      "camrip": false,
      "blocked_countries": [],
      "created_at": "2020-01-27T14:25:31Z",
      "updated_at": "2020-01-27T14:25:31Z"
    },
    {
      "id": "movie-48347",
      "type": "anime",
      "link": "",
      "title": "Большие войны",
      "title_orig": "Daisenki",
      "other_title": "Большая Война: Бог Пустыни / Big Wars: Kami Utsu Akaki Kouya ni",
      "translation": {
        "id": 767,
        "title": "SHIZA Project",
        "type": "voice"
      },
      "year": 1993,
      "kinopoisk_id": "335790",
      "imdb_id": "tt0150259",
      "worldart_link": "http://www.world-art.ru/animation/animation.php?id=3020",
      "shikimori_id": "2622",
      "quality": "DVDRip",
      "camrip": false,
      "blocked_countries": [],
      "created_at": "2020-01-27T14:24:28Z",
      "updated_at": "2020-01-27T14:24:28Z"
    },
    {
      "id": "serial-21813",
      "type": "anime-serial",
      "link": "",
      "title": "Призрак в доспехах OVA",
      "title_orig": "Koukaku Kidoutai Arise: Ghost in the Shell",
      "other_title": "Дух в стальной плоти: У истоков / Призрак в Доспехах - Происхождение",
      "translation": {
        "id": 767,
        "title": "SHIZA Project",
        "type": "voice"
      },
      "year": 2013,
      "last_season": 1,
      "last_episode": 4,
      "episodes_count": 4,
      "worldart_link": "http://www.world-art.ru/animation/animation.php?id=1377",
      "shikimori_id": "19191",
      "quality": "BDRip 720p",
      "camrip": false,
      "blocked_countries": [],
      "blocked_seasons": {},
      "created_at": "2020-01-27T14:04:20Z",
      "updated_at": "2020-01-27T14:04:20Z"
    },
    {
      "id": "serial-8166",
      "type": "anime-serial",
      "link": "",
      "title": "Шутки чокнутой столицы ONA-2",
      "title_orig": "Kyousougiga",
      "other_title": "Шизанутая столица",
      "translation": {
        "id": 767,
        "title": "SHIZA Project",
        "type": "voice"
      },
      "year": 2012,
      "last_season": 2,
      "last_episode": 5,
      "episodes_count": 5,
      "worldart_link": "http://www.world-art.ru/animation/animation.php?id=1152",
      "shikimori_id": "15359",
      "quality": "BDRip 720p",
      "camrip": false,
      "blocked_countries": [],
      "blocked_seasons": {},
      "created_at": "2018-01-02T03:02:02Z",
      "updated_at": "2020-01-27T13:54:07Z"
    },
    {
      "id": "serial-3952",
      "type": "foreign-serial",
      "link": "",
      "title": "Босс и я",
      "title_orig": "Shan Shan Lai Le",
      "other_title": "Шеф и я / Пора кушать, Шань Шань! / Boss & Me",
      "translation": {
        "id": 674,
        "title": "Люб. Одноголосый",
        "type": "voice"
      },
      "year": 2014,
      "last_season": 1,
      "last_episode": 33,
      "episodes_count": 33,
      "kinopoisk_id": "906890",
      "imdb_id": "tt6186406",
      "quality": "HDTVRip 720p",
      "camrip": false,
      "blocked_countries": [],
      "blocked_seasons": {},
      "created_at": "2017-05-30T12:04:40Z",
      "updated_at": "2020-01-27T13:52:54Z"
    },
    {
      "id": "serial-21811",
      "type": "anime-serial",
      "link": "",
      "title": "Санка Рэа OVA",
      "title_orig": "Sankarea OVA",
      "other_title": "さんかれあ OVA",
      "translation": {
        "id": 767,
        "title": "SHIZA Project",
        "type": "voice"
      },
      "year": 2012,
      "last_season": 1,
      "last_episode": 2,
      "episodes_count": 2,
      "worldart_link": "http://www.world-art.ru/animation/animation.php?id=1887",
      "shikimori_id": "13055",
      "quality": "BDRip 720p",
      "camrip": false,
      "blocked_countries": [],
      "blocked_seasons": {},
      "created_at": "2020-01-27T13:51:58Z",
      "updated_at": "2020-01-27T13:51:58Z"
    },
    {
      "id": "serial-21810",
      "type": "anime-serial",
      "link": "",
      "title": "Святой рыцарь",
      "title_orig": "Holy Knight",
      "other_title": "Святой рыцарь OVA",
      "translation": {
        "id": 767,
        "title": "SHIZA Project",
        "type": "voice"
      },
      "year": 2012,
      "last_season": 1,
      "last_episode": 2,
      "episodes_count": 2,
      "kinopoisk_id": "710133",
      "imdb_id": "tt3685006",
      "worldart_link": "http://www.world-art.ru/animation/animation.php?id=1997",
      "shikimori_id": "11005",
      "quality": "BDRip 720p",
      "camrip": false,
      "blocked_countries": [],
      "blocked_seasons": {},
      "created_at": "2020-01-27T13:49:16Z",
      "updated_at": "2020-01-27T13:49:16Z"
    },
    {
      "id": "movie-48346",
      "type": "anime",
      "link": "",
      "title": "Боб на колесах",
      "title_orig": "Riding Bean",
      "other_title": "Перевозчик Бин",
      "translation": {
        "id": 767,
        "title": "SHIZA Project",
        "type": "voice"
      },
      "year": 1989,
      "kinopoisk_id": "335179",
      "imdb_id": "tt0098202",
      "worldart_link": "http://www.world-art.ru/animation/animation.php?id=218",
      "shikimori_id": "917",
      "quality": "BDRip 720p",
      "camrip": false,
      "blocked_countries": [],
      "created_at": "2020-01-27T13:46:50Z",
      "updated_at": "2020-01-27T13:46:50Z"
    },
    {
      "id": "movie-48345",
      "type": "anime",
      "link": "",
      "title": "Признание Фумико",
      "title_orig": "Fumiko no Kokuhaku",
      "other_title": "Fumiko's Confession",
      "translation": {
        "id": 767,
        "title": "SHIZA Project",
        "type": "voice"
      },
      "year": 2009,
      "kinopoisk_id": "893252",
      "imdb_id": "tt3970004",
      "worldart_link": "http://www.world-art.ru/animation/animation.php?id=7695",
      "shikimori_id": "8187",
      "quality": "BDRip 720p",
      "camrip": false,
      "blocked_countries": [],
      "created_at": "2020-01-27T13:45:51Z",
      "updated_at": "2020-01-27T13:45:51Z"
    },
    {
      "id": "serial-21809",
      "type": "anime-serial",
      "link": "",
      "title": "Мозайка",
      "title_orig": "Eiyuu Gaiden Mozaicka",
      "other_title": "英雄凱伝モザイカ",
      "translation": {
        "id": 767,
        "title": "SHIZA Project",
        "type": "voice"
      },
      "year": 1991,
      "last_season": 1,
      "last_episode": 4,
      "episodes_count": 4,
      "kinopoisk_id": "879858",
      "imdb_id": "tt3895474",
      "worldart_link": "http://www.world-art.ru/animation/animation.php?id=6219",
      "shikimori_id": "8855",
      "quality": "DVDRip",
      "camrip": false,
      "blocked_countries": [],
      "blocked_seasons": {},
      "created_at": "2020-01-27T13:32:33Z",
      "updated_at": "2020-01-27T13:32:33Z"
    },
    {
      "id": "serial-21808",
      "type": "anime-serial",
      "link": "",
      "title": "Мобильный воин Гандам: Скрытая Однолетняя война",
      "title_orig": "Kidou Senshi Gundam MS IGLOO: Ichinen Sensou Hiwa",
      "other_title": "Мобильный воин ГАНДАМ - Скрытая Однолетняя война",
      "translation": {
        "id": 767,
        "title": "SHIZA Project",
        "type": "voice"
      },
      "year": 2004,
      "last_season": 1,
      "last_episode": 3,
      "episodes_count": 3,
      "imdb_id": "tt2328145",
      "worldart_link": "http://www.world-art.ru/animation/animation.php?id=4470",
      "shikimori_id": "1917",
      "quality": "BDRip",
      "camrip": false,
      "blocked_countries": [],
      "blocked_seasons": {},
      "created_at": "2020-01-27T13:30:31Z",
      "updated_at": "2020-01-27T13:30:31Z"
    },
    {
      "id": "serial-21807",
      "type": "anime-serial",
      "link": "",
      "title": "Звездная карта",
      "title_orig": "Maps",
      "other_title": "Звёздные карты",
      "translation": {
        "id": 767,
        "title": "SHIZA Project",
        "type": "voice"
      },
      "year": 1994,
      "last_season": 1,
      "last_episode": 4,
      "episodes_count": 4,
      "kinopoisk_id": "351332",
      "imdb_id": "tt0110464",
      "worldart_link": "http://www.world-art.ru/animation/animation.php?id=3852",
      "shikimori_id": "1620",
      "quality": "DVDRip",
      "camrip": false,
      "blocked_countries": [],
      "blocked_seasons": {},
      "created_at": "2020-01-27T13:26:54Z",
      "updated_at": "2020-01-27T13:26:54Z"
    },
    {
      "id": "movie-48344",
      "type": "anime",
      "link": "",
      "title": "Бронированные воины Вотомы",
      "title_orig": "Soukou Kihei Votoms: Red Shoulder Document - Yabou no Roots",
      "other_title": "装甲騎兵ボトムズ　レッドショルダードキュメント野望のルーツ / 装甲騎兵ボトムズ レッドショルダードキュメント野望のルーツ",
      "translation": {
        "id": 767,
        "title": "SHIZA Project",
        "type": "voice"
      },
      "year": 1988,
      "worldart_link": "http://www.world-art.ru/animation/animation.php?id=6131",
      "shikimori_id": "2585",
      "quality": "DVDRip",
      "camrip": false,
      "blocked_countries": [],
      "created_at": "2020-01-27T13:24:08Z",
      "updated_at": "2020-01-27T13:24:08Z"
    },
    {
      "id": "serial-4362",
      "type": "anime-serial",
      "link": "",
      "title": "Теннис [ТВ-9]",
      "title_orig": "Teekyuu 9",
      "other_title": "Те-кю 9 / Дети цветов 9 / Теннис 9",
      "translation": {
        "id": 609,
        "title": "AniDUB",
        "type": "voice"
      },
      "year": 2017,
      "last_season": 9,
      "last_episode": 12,
      "episodes_count": 12,
      "kinopoisk_id": "1005025",
      "imdb_id": "tt2390066",
      "worldart_link": "http://www.world-art.ru/animation/animation.php?id=9237",
      "shikimori_id": "35370",
      "quality": "HDTVRip 720p",
      "camrip": false,
      "blocked_countries": [],
      "blocked_seasons": {},
      "created_at": "2017-07-24T23:18:42Z",
      "updated_at": "2020-01-27T13:21:36Z"
    },
    {
      "id": "serial-2105",
      "type": "anime-serial",
      "link": "",
      "title": "Теннис [ТВ-8]",
      "title_orig": "Teekyuu 8",
      "other_title": "Те-кю 8 / Дети цветов 8",
      "translation": {
        "id": 609,
        "title": "AniDUB",
        "type": "voice"
      },
      "year": 2016,
      "last_season": 8,
      "last_episode": 12,
      "episodes_count": 12,
      "kinopoisk_id": "1005025",
      "imdb_id": "tt2390066",
      "worldart_link": "http://www.world-art.ru/animation/animation.php?id=8884",
      "shikimori_id": "33811",
      "quality": "HDTVRip 720p",
      "camrip": false,
      "blocked_countries": [],
      "blocked_seasons": {},
      "created_at": "2017-01-09T18:16:36Z",
      "updated_at": "2020-01-27T13:21:10Z"
    },
    {
      "id": "serial-5822",
      "type": "anime-serial",
      "link": "",
      "title": "Теннис [ТВ-7]",
      "title_orig": "Teekyuu 7",
      "other_title": "Дети цветов 7",
      "translation": {
        "id": 609,
        "title": "AniDUB",
        "type": "voice"
      },
      "year": 2016,
      "last_season": 7,
      "last_episode": 12,
      "episodes_count": 12,
      "kinopoisk_id": "1005025",
      "imdb_id": "tt2390066",
      "worldart_link": "http://www.world-art.ru/animation/animation.php?id=8597",
      "shikimori_id": "32228",
      "quality": "HDTVRip 720p",
      "camrip": false,
      "blocked_countries": [],
      "blocked_seasons": {},
      "created_at": "2017-11-11T22:40:53Z",
      "updated_at": "2020-01-27T13:20:42Z"
    },
    {
      "id": "serial-5820",
      "type": "anime-serial",
      "link": "",
      "title": "Теннис [ТВ-6]",
      "title_orig": "Teekyuu 6",
      "other_title": "Дети цветов 6",
      "translation": {
        "id": 609,
        "title": "AniDUB",
        "type": "voice"
      },
      "year": 2015,
      "last_season": 6,
      "last_episode": 12,
      "episodes_count": 12,
      "kinopoisk_id": "1005025",
      "imdb_id": "tt2390066",
      "worldart_link": "http://www.world-art.ru/animation/animation.php?id=8469",
      "shikimori_id": "31440",
      "quality": "HDTVRip 720p",
      "camrip": false,
      "blocked_countries": [],
      "blocked_seasons": {},
      "created_at": "2017-11-11T22:40:21Z",
      "updated_at": "2020-01-27T13:10:55Z"
    },
    {
      "id": "serial-5819",
      "type": "anime-serial",
      "link": "",
      "title": "Теннис [ТВ-5]",
      "title_orig": "Teekyuu 5",
      "other_title": "Дети цветов 5",
      "translation": {
        "id": 609,
        "title": "AniDUB",
        "type": "voice"
      },
      "year": 2015,
      "last_season": 5,
      "last_episode": 12,
      "episodes_count": 12,
      "kinopoisk_id": "1005025",
      "imdb_id": "tt2390066",
      "worldart_link": "http://www.world-art.ru/animation/animation.php?id=8326",
      "shikimori_id": "30567",
      "quality": "HDTVRip 720p",
      "camrip": false,
      "blocked_countries": [],
      "blocked_seasons": {},
      "created_at": "2017-11-11T22:39:48Z",
      "updated_at": "2020-01-27T13:10:04Z"
    },
    {
      "id": "serial-5818",
      "type": "anime-serial",
      "link": "",
      "title": "Теннис [ТВ-4]",
      "title_orig": "Teekyuu 4",
      "other_title": "Те-кю 4 / Дети цветов 4",
      "translation": {
        "id": 609,
        "title": "AniDUB",
        "type": "voice"
      },
      "year": 2015,
      "last_season": 4,
      "last_episode": 14,
      "episodes_count": 14,
      "kinopoisk_id": "1005025",
      "imdb_id": "tt2390066",
      "worldart_link": "http://www.world-art.ru/animation/animation.php?id=3746",
      "shikimori_id": "26395",
      "quality": "HDTVRip 720p",
      "camrip": false,
      "blocked_countries": [],
      "blocked_seasons": {},
      "created_at": "2017-11-11T22:39:11Z",
      "updated_at": "2020-01-27T13:09:31Z"
    },
    {
      "id": "serial-5816",
      "type": "anime-serial",
      "link": "",
      "title": "Теннис [ТВ-3]",
      "title_orig": "Teekyuu 3",
      "other_title": "Те-кю 3 / Дети цветов 3",
      "translation": {
        "id": 609,
        "title": "AniDUB",
        "type": "voice"
      },
      "year": 2013,
      "last_season": 3,
      "last_episode": 14,
      "episodes_count": 14,
      "kinopoisk_id": "1005025",
      "imdb_id": "tt2390066",
      "worldart_link": "http://www.world-art.ru/animation/animation.php?id=1704",
      "shikimori_id": "20473",
      "quality": "HDTVRip 720p",
      "camrip": false,
      "blocked_countries": [],
      "blocked_seasons": {},
      "created_at": "2017-11-11T22:38:29Z",
      "updated_at": "2020-01-27T13:08:51Z"
    },
    {
      "id": "serial-5815",
      "type": "anime-serial",
      "link": "",
      "title": "Теннис [ТВ-2]",
      "title_orig": "Teekyuu 2",
      "other_title": "Дети цветов 2",
      "translation": {
        "id": 609,
        "title": "AniDUB",
        "type": "voice"
      },
      "year": 2013,
      "last_season": 2,
      "last_episode": 14,
      "episodes_count": 14,
      "kinopoisk_id": "1005025",
      "imdb_id": "tt2390066",
      "worldart_link": "http://www.world-art.ru/animation/animation.php?id=1432",
      "shikimori_id": "18121",
      "quality": "HDTVRip 720p",
      "camrip": false,
      "blocked_countries": [],
      "blocked_seasons": {},
      "created_at": "2017-11-11T22:37:52Z",
      "updated_at": "2020-01-27T13:08:02Z"
    },
    {
      "id": "serial-21806",
      "type": "anime-serial",
      "link": "",
      "title": "Теннис [ТВ-2]",
      "title_orig": "Teekyuu 2",
      "other_title": "Дети цветов 2\t/ Те-кю 2",
      "translation": {
        "id": 767,
        "title": "SHIZA Project",
        "type": "voice"
      },
      "year": 2012,
      "last_season": 2,
      "last_episode": 14,
      "episodes_count": 14,
      "kinopoisk_id": "1005025",
      "imdb_id": "tt2390066",
      "worldart_link": "http://www.world-art.ru/animation/animation.php?id=1432",
      "shikimori_id": "18121",
      "quality": "BDRip 720p",
      "camrip": false,
      "blocked_countries": [],
      "blocked_seasons": {},
      "created_at": "2020-01-27T13:07:09Z",
      "updated_at": "2020-01-27T13:07:09Z"
    },
    {
      "id": "serial-21735",
      "type": "anime-serial",
      "link": "",
      "title": "Дело ведет юный детектив Киндаити",
      "title_orig": "Kindaichi Shounen no Jikenbo (1997)",
      "other_title": "Дело ведёт юный детектив Киндаити",
      "translation": {
        "id": 869,
        "title": "Субтитры",
        "type": "subtitles"
      },
      "year": 1997,
      "last_season": 1,
      "last_episode": 148,
      "episodes_count": 148,
      "kinopoisk_id": "408735",
      "imdb_id": "tt0348952",
      "worldart_link": "http://www.world-art.ru/animation/animation.php?id=4073",
      "shikimori_id": "2076",
      "quality": "DVDRip",
      "camrip": false,
      "blocked_countries": [],
      "blocked_seasons": {},
      "created_at": "2020-01-26T13:41:53Z",
      "updated_at": "2020-01-27T12:56:34Z"
    },
    {
      "id": "serial-21804",
      "type": "anime-serial",
      "link": "",
      "title": "Мобильный воин ГАНДАМ: Апокалипсис 0079",
      "title_orig": "Kidou Senshi Gundam MS IGLOO: Mokushiroku 0079",
      "other_title": "Мобильный воин ГАНДАМ - Апокалипсис 0079",
      "translation": {
        "id": 767,
        "title": "SHIZA Project",
        "type": "voice"
      },
      "year": 2006,
      "last_season": 1,
      "last_episode": 3,
      "episodes_count": 3,
      "imdb_id": "tt7127518",
      "worldart_link": "http://www.world-art.ru/animation/animation.php?id=5506",
      "shikimori_id": "1916",
      "quality": "BDRip",
      "camrip": false,
      "blocked_countries": [],
      "blocked_seasons": {},
      "created_at": "2020-01-27T12:34:19Z",
      "updated_at": "2020-01-27T12:34:19Z"
    },
    {
      "id": "movie-48341",
      "type": "anime",
      "link": "",
      "title": "Крушила Джо OVA-2",
      "title_orig": "Crusher Joe: Saishuu Heiki Ash",
      "other_title": "Крушила Джо - Разрушительное оружие \"Пепел\" / Crusher Joe: Final Weapon Ash",
      "translation": {
        "id": 767,
        "title": "SHIZA Project",
        "type": "voice"
      },
      "year": 1989,
      "kinopoisk_id": "298101",
      "imdb_id": "tt0158569",
      "worldart_link": "http://www.world-art.ru/animation/animation.php?id=3413",
      "shikimori_id": "2696",
      "quality": "DVDRip",
      "camrip": false,
      "blocked_countries": [],
      "created_at": "2020-01-27T12:32:21Z",
      "updated_at": "2020-01-27T12:32:21Z"
    },
    {
      "id": "serial-21803",
      "type": "anime-serial",
      "link": "",
      "title": "Хладнокровный Ходзуки OVA",
      "title_orig": "Hoozuki no Reitetsu OVA",
      "other_title": "鬼灯の冷徹 OVA",
      "translation": {
        "id": 767,
        "title": "SHIZA Project",
        "type": "voice"
      },
      "year": 2014,
      "last_season": 1,
      "last_episode": 3,
      "episodes_count": 3,
      "worldart_link": "http://www.world-art.ru/animation/animation.php?id=2371",
      "shikimori_id": "24471",
      "quality": "DVDRip",
      "camrip": false,
      "blocked_countries": [],
      "blocked_seasons": {},
      "created_at": "2020-01-27T12:28:05Z",
      "updated_at": "2020-01-27T12:28:05Z"
    },
    {
      "id": "serial-21802",
      "type": "anime-serial",
      "link": "",
      "title": "МангаЧки!",
      "title_orig": "Mangirl!",
      "other_title": "Мангачки! / Мангачки / まんがーる!",
      "translation": {
        "id": 767,
        "title": "SHIZA Project",
        "type": "voice"
      },
      "year": 2013,
      "last_season": 1,
      "last_episode": 13,
      "episodes_count": 13,
      "kinopoisk_id": "730470",
      "imdb_id": "tt2596090",
      "worldart_link": "http://www.world-art.ru/animation/animation.php?id=1295",
      "shikimori_id": "14045",
      "quality": "HDTVRip 720p",
      "camrip": false,
      "blocked_countries": [],
      "blocked_seasons": {},
      "created_at": "2020-01-27T12:25:54Z",
      "updated_at": "2020-01-27T12:25:54Z"
    },
    {
      "id": "serial-21801",
      "type": "anime-serial",
      "link": "",
      "title": "Повелитель Тьмы на подработке!",
      "title_orig": "Hataraku Maou-sama!",
      "other_title": "Сатана на подработке!",
      "translation": {
        "id": 767,
        "title": "SHIZA Project",
        "type": "voice"
      },
      "year": 2013,
      "last_season": 1,
      "last_episode": 13,
      "episodes_count": 13,
      "kinopoisk_id": "760019",
      "imdb_id": "tt2622982",
      "worldart_link": "http://www.world-art.ru/animation/animation.php?id=6807",
      "shikimori_id": "15809",
      "quality": "BDRip 720p",
      "camrip": false,
      "blocked_countries": [],
      "blocked_seasons": {},
      "created_at": "2020-01-27T12:22:12Z",
      "updated_at": "2020-01-27T12:22:12Z"
    },
    {
      "id": "serial-21800",
      "type": "anime-serial",
      "link": "",
      "title": "Токийский гуль [ТВ-1]",
      "title_orig": "Tokyo Ghoul",
      "other_title": "Токийский упырь (1 сезон)",
      "translation": {
        "id": 767,
        "title": "SHIZA Project",
        "type": "voice"
      },
      "year": 2014,
      "last_season": 1,
      "last_episode": 12,
      "episodes_count": 12,
      "kinopoisk_id": "841681",
      "imdb_id": "tt3741634",
      "worldart_link": "http://www.world-art.ru/animation/animation.php?id=2300",
      "shikimori_id": "22319",
      "quality": "BDRip 720p",
      "camrip": false,
      "blocked_countries": [],
      "blocked_seasons": {},
      "created_at": "2020-01-27T12:13:55Z",
      "updated_at": "2020-01-27T12:13:55Z"
    },
    {
      "id": "serial-21799",
      "type": "anime-serial",
      "link": "",
      "title": "Жаркие деньки [ТВ-1]",
      "title_orig": "Dog Days",
      "other_title": "Собачья жизнь",
      "translation": {
        "id": 767,
        "title": "SHIZA Project",
        "type": "voice"
      },
      "year": 2011,
      "last_season": 1,
      "last_episode": 13,
      "episodes_count": 13,
      "kinopoisk_id": "692459",
      "imdb_id": "tt2082624",
      "worldart_link": "http://www.world-art.ru/animation/animation.php?id=8162",
      "shikimori_id": "10155",
      "quality": "BDRip 720p",
      "camrip": false,
      "blocked_countries": [],
      "blocked_seasons": {},
      "created_at": "2020-01-27T12:10:36Z",
      "updated_at": "2020-01-27T12:10:36Z"
    },
    {
      "id": "serial-21798",
      "type": "anime-serial",
      "link": "",
      "title": "Гатчамен: Общество",
      "title_orig": "Gatchaman Crowds",
      "other_title": "Отряд Галактика - Куча-Мала / Отряд «Галактика» / Гатчамэн: Отряд Галактика",
      "translation": {
        "id": 767,
        "title": "SHIZA Project",
        "type": "voice"
      },
      "year": 2013,
      "last_season": 1,
      "last_episode": 12,
      "episodes_count": 12,
      "kinopoisk_id": "808315",
      "imdb_id": "tt2959370",
      "worldart_link": "http://www.world-art.ru/animation/animation.php?id=1424",
      "shikimori_id": "18229",
      "quality": "BDRip 720p",
      "camrip": false,
      "blocked_countries": [],
      "blocked_seasons": {},
      "created_at": "2020-01-27T12:06:53Z",
      "updated_at": "2020-01-27T12:06:53Z"
    },
    {
      "id": "serial-21797",
      "type": "anime-serial",
      "link": "",
      "title": "Чара-хранители! (сезон первый)",
      "title_orig": "Shugo Chara!!",
      "other_title": "Shugokyara",
      "translation": {
        "id": 767,
        "title": "SHIZA Project",
        "type": "voice"
      },
      "year": 2007,
      "last_season": 1,
      "last_episode": 30,
      "episodes_count": 30,
      "kinopoisk_id": "471156",
      "imdb_id": "tt1133480",
      "worldart_link": "http://www.world-art.ru/animation/animation.php?id=6635",
      "shikimori_id": "2923",
      "quality": "HDTVRip 720p",
      "camrip": false,
      "blocked_countries": [],
      "blocked_seasons": {},
      "created_at": "2020-01-27T12:02:28Z",
      "updated_at": "2020-01-27T12:02:28Z"
    },
    {
      "id": "serial-21796",
      "type": "anime-serial",
      "link": "",
      "title": "Формула жизни",
      "title_orig": "Yuyushiki",
      "other_title": "Формула \"ЮЮ\" / В стиле ЮЮ",
      "translation": {
        "id": 767,
        "title": "SHIZA Project",
        "type": "voice"
      },
      "year": 2013,
      "last_season": 1,
      "last_episode": 12,
      "episodes_count": 12,
      "kinopoisk_id": "757704",
      "imdb_id": "tt2622978",
      "worldart_link": "http://www.world-art.ru/animation/animation.php?id=1153",
      "shikimori_id": "15911",
      "quality": "HDTVRip 720p",
      "camrip": false,
      "blocked_countries": [],
      "blocked_seasons": {},
      "created_at": "2020-01-27T11:55:26Z",
      "updated_at": "2020-01-27T11:55:26Z"
    },
    {
      "id": "movie-48342",
      "type": "foreign-movie",
      "link": "",
      "title": "Зов героев",
      "title_orig": "Wei cheng jian ba",
      "translation": {
        "id": 620,
        "title": "GREEN TEA",
        "type": "voice"
      },
      "year": 2016,
      "kinopoisk_id": "988954",
      "imdb_id": "tt5842624",
      "quality": "BDRip 720p",
      "camrip": false,
      "blocked_countries": [],
      "created_at": "2020-01-27T11:41:00Z",
      "updated_at": "2020-01-27T11:41:00Z"
    },
    {
      "id": "movie-48343",
      "type": "foreign-movie",
      "link": "",
      "title": "Блюз младенца",
      "title_orig": "Gui ying: Baby Blues",
      "translation": {
        "id": 613,
        "title": "DeadSno & den904",
        "type": "voice"
      },
      "year": 2013,
      "kinopoisk_id": "707323",
      "imdb_id": "tt2375318",
      "quality": "BDRip 720p",
      "camrip": false,
      "blocked_countries": [],
      "created_at": "2020-01-27T11:39:42Z",
      "updated_at": "2020-01-27T11:39:42Z"
    },
    {
      "id": "serial-21795",
      "type": "anime-serial",
      "link": "",
      "title": "Хаятэ, боевой дворецкий [ТВ-4]",
      "title_orig": "Hayate no Gotoku! Cuties",
      "other_title": "Хаятэ, боевой дворецкий: Милашки / Хаятэ, боевой дворецкий ТВ-4 / Хаятэ, боевой дворецкий (четвертый сезон)",
      "translation": {
        "id": 767,
        "title": "SHIZA Project",
        "type": "voice"
      },
      "year": 2013,
      "last_season": 4,
      "last_episode": 12,
      "episodes_count": 12,
      "kinopoisk_id": "1040190",
      "imdb_id": "tt5647272",
      "worldart_link": "http://www.world-art.ru/animation/animation.php?id=1449",
      "shikimori_id": "16982",
      "quality": "BDRip 720p",
      "camrip": false,
      "blocked_countries": [],
      "blocked_seasons": {},
      "created_at": "2020-01-27T10:53:42Z",
      "updated_at": "2020-01-27T10:53:42Z"
    },
    {
      "id": "serial-21794",
      "type": "anime-serial",
      "link": "",
      "title": "Одному лишь Богу ведомый мир [ТВ-3]",
      "title_orig": "Kami nomi zo Shiru Sekai: Megami Hen",
      "other_title": "Одному лишь Богу ведомый мир: Богини / Мир, ведомый лишь богу: Богини / Одному лишь Богу ведомый мир 3 / Одному лишь Богу ведомый мир III: Богини",
      "translation": {
        "id": 767,
        "title": "SHIZA Project",
        "type": "voice"
      },
      "year": 2013,
      "last_season": 3,
      "last_episode": 12,
      "episodes_count": 12,
      "kinopoisk_id": "632810",
      "imdb_id": "tt1899022",
      "worldart_link": "http://www.world-art.ru/animation/animation.php?id=1650",
      "shikimori_id": "16706",
      "quality": "BDRip 720p",
      "camrip": false,
      "blocked_countries": [],
      "blocked_seasons": {},
      "created_at": "2020-01-27T10:51:48Z",
      "updated_at": "2020-01-27T10:51:48Z"
    },
    {
      "id": "serial-21793",
      "type": "anime-serial",
      "link": "",
      "title": "Мой «комплекс братика» морали не остановить!",
      "title_orig": "Onii-chan Dakedo Ai Sae Areba Kankei Nai yo ne!",
      "other_title": "Мой комплекс брата морали не остановить / Пока есть любовь, не имеет значения, что он мой брат",
      "translation": {
        "id": 767,
        "title": "SHIZA Project",
        "type": "voice"
      },
      "year": 2012,
      "last_season": 1,
      "last_episode": 12,
      "episodes_count": 12,
      "kinopoisk_id": "728047",
      "imdb_id": "tt2390038",
      "worldart_link": "http://www.world-art.ru/animation/animation.php?id=1032",
      "shikimori_id": "14199",
      "quality": "BDRip 720p",
      "camrip": false,
      "blocked_countries": [],
      "blocked_seasons": {},
      "created_at": "2020-01-27T10:35:40Z",
      "updated_at": "2020-01-27T10:35:40Z"
    },
    {
      "id": "serial-21792",
      "type": "anime-serial",
      "link": "",
      "title": "Хаккэндэн: Легенда о восьми псах Востока [ТВ-2]",
      "title_orig": "Hakkenden: Touhou Hakken Ibun 2",
      "other_title": "Хаккэндэн: Легенда о восьми Псах Востока (сериал) / Хаккенден - Легенда о восьми псах востока (второй сезон)",
      "translation": {
        "id": 767,
        "title": "SHIZA Project",
        "type": "voice"
      },
      "year": 2013,
      "last_season": 2,
      "last_episode": 13,
      "episodes_count": 13,
      "kinopoisk_id": "724677",
      "imdb_id": "tt2575722",
      "worldart_link": "http://www.world-art.ru/animation/animation.php?id=1485",
      "shikimori_id": "18055",
      "quality": "HDTVRip 720p",
      "camrip": false,
      "blocked_countries": [],
      "blocked_seasons": {},
      "created_at": "2020-01-27T10:32:59Z",
      "updated_at": "2020-01-27T10:32:59Z"
    },
    {
      "id": "serial-21791",
      "type": "anime-serial",
      "link": "",
      "title": "Кружок по страйкболу женской гимназии Стелла",
      "title_orig": "Stella Jogakuin Koutouka C3-bu",
      "other_title": "Клуб К3 / Кружок по страйкболу женской гимназии «Стелла»",
      "translation": {
        "id": 767,
        "title": "SHIZA Project",
        "type": "voice"
      },
      "year": 2013,
      "last_season": 1,
      "last_episode": 13,
      "episodes_count": 13,
      "imdb_id": "tt2904622",
      "worldart_link": "http://www.world-art.ru/animation/animation.php?id=1411",
      "shikimori_id": "17821",
      "quality": "BDRip 720p",
      "camrip": false,
      "blocked_countries": [],
      "blocked_seasons": {},
      "created_at": "2020-01-27T10:29:36Z",
      "updated_at": "2020-01-27T10:29:36Z"
    },
    {
      "id": "serial-21790",
      "type": "anime-serial",
      "link": "",
      "title": "Симфогир [ТВ-2]",
      "title_orig": "Senki Zesshou Symphogear G",
      "other_title": "Симфогир: Песнь боевых принцесс / Симфогир Джи - Песнь Боевых Принцесс",
      "translation": {
        "id": 767,
        "title": "SHIZA Project",
        "type": "voice"
      },
      "year": 2013,
      "last_season": 2,
      "last_episode": 13,
      "episodes_count": 13,
      "kinopoisk_id": "762157",
      "imdb_id": "tt2859274",
      "worldart_link": "http://www.world-art.ru/animation/animation.php?id=6590",
      "shikimori_id": "15793",
      "quality": "BDRip 720p",
      "camrip": false,
      "blocked_countries": [],
      "blocked_seasons": {},
      "created_at": "2020-01-27T10:23:52Z",
      "updated_at": "2020-01-27T10:23:52Z"
    },
    {
      "id": "serial-21789",
      "type": "anime-serial",
      "link": "",
      "title": "Цветы зла",
      "title_orig": "Aku no hana",
      "other_title": "Flowers of Evil",
      "translation": {
        "id": 767,
        "title": "SHIZA Project",
        "type": "voice"
      },
      "year": 2013,
      "last_season": 1,
      "last_episode": 13,
      "episodes_count": 13,
      "kinopoisk_id": "760136",
      "imdb_id": "tt2636546",
      "worldart_link": "http://www.world-art.ru/animation/animation.php?id=1162",
      "shikimori_id": "16201",
      "quality": "BDRip 720p",
      "camrip": false,
      "blocked_countries": [],
      "blocked_seasons": {},
      "created_at": "2020-01-27T10:02:18Z",
      "updated_at": "2020-01-27T10:02:18Z"
    },
    {
      "id": "serial-21788",
      "type": "anime-serial",
      "link": "",
      "title": "Истории, сезон второй",
      "title_orig": "Monogatari Series: Second Season",
      "other_title": "Цикл историй: второй сезон",
      "translation": {
        "id": 767,
        "title": "SHIZA Project",
        "type": "voice"
      },
      "year": 2013,
      "last_season": 2,
      "last_episode": 23,
      "episodes_count": 23,
      "kinopoisk_id": "817892",
      "imdb_id": "tt2922300",
      "worldart_link": "http://www.world-art.ru/animation/animation.php?id=1535",
      "shikimori_id": "17074",
      "quality": "BDRip 720p",
      "camrip": false,
      "blocked_countries": [],
      "blocked_seasons": {},
      "created_at": "2020-01-27T09:37:51Z",
      "updated_at": "2020-01-27T09:37:51Z"
    },
    {
      "id": "serial-21787",
      "type": "anime-serial",
      "link": "",
      "title": "Демоны старшей школы [ТВ-2]",
      "title_orig": "High School DxD New: Gekkou Koutei no Excalibur",
      "other_title": "Высшая школа DxD / Демоны старшей школы (второй сезон)",
      "translation": {
        "id": 767,
        "title": "SHIZA Project",
        "type": "voice"
      },
      "year": 2013,
      "last_season": 2,
      "last_episode": 12,
      "episodes_count": 12,
      "kinopoisk_id": "666587",
      "imdb_id": "tt2230051",
      "worldart_link": "http://www.world-art.ru/animation/animation.php?id=2782",
      "shikimori_id": "15451",
      "quality": "BDRip 720p",
      "camrip": false,
      "blocked_countries": [],
      "blocked_seasons": {},
      "created_at": "2020-01-27T09:28:59Z",
      "updated_at": "2020-01-27T09:28:59Z"
    },
    {
      "id": "movie-48330",
      "type": "foreign-movie",
      "link": "",
      "title": "Злодей",
      "title_orig": "The Villain",
      "translation": {
        "id": 670,
        "title": "Синема УС",
        "type": "voice"
      },
      "year": 2018,
      "kinopoisk_id": "1018548",
      "imdb_id": "tt6203302",
      "quality": "WEB-DLRip 720p",
      "camrip": false,
      "blocked_countries": [],
      "created_at": "2020-01-27T09:19:48Z",
      "updated_at": "2020-01-27T09:19:48Z"
    },
    {
      "id": "movie-48333",
      "type": "foreign-movie",
      "link": "",
      "title": "Невидимый",
      "title_orig": "Adrishya",
      "translation": {
        "id": 670,
        "title": "Синема УС",
        "type": "voice"
      },
      "year": 2017,
      "kinopoisk_id": "1108174",
      "imdb_id": "tt7476874",
      "quality": "WEB-DLRip 720p",
      "camrip": false,
      "blocked_countries": [],
      "created_at": "2020-01-27T09:18:20Z",
      "updated_at": "2020-01-27T09:18:20Z"
    },
    {
      "id": "serial-21786",
      "type": "anime-serial",
      "link": "",
      "title": "Фейри Тейл [ТВ-1]",
      "title_orig": "Fairy Tail",
      "other_title": "Сказка о хвосте феи / Хвост Феи (1 сезон)",
      "translation": {
        "id": 767,
        "title": "SHIZA Project",
        "type": "voice"
      },
      "year": 2009,
      "last_season": 1,
      "last_episode": 175,
      "episodes_count": 175,
      "kinopoisk_id": "480158",
      "imdb_id": "tt1528406",
      "worldart_link": "http://www.world-art.ru/animation/animation.php?id=7446",
      "shikimori_id": "6702",
      "quality": "BDRip 720p",
      "camrip": false,
      "blocked_countries": [],
      "blocked_seasons": {},
      "created_at": "2020-01-27T09:17:17Z",
      "updated_at": "2020-01-27T09:17:17Z"
    },
    {
      "id": "serial-21785",
      "type": "anime-serial",
      "link": "",
      "title": "Город, в котором ты живёшь [ТВ]",
      "title_orig": "Kimi no Iru Machi",
      "other_title": "A Town Where You Live",
      "translation": {
        "id": 767,
        "title": "SHIZA Project",
        "type": "voice"
      },
      "year": 2013,
      "last_season": 1,
      "last_episode": 12,
      "episodes_count": 12,
      "kinopoisk_id": "906911",
      "imdb_id": "tt6516482",
      "worldart_link": "http://www.world-art.ru/animation/animation.php?id=1405",
      "shikimori_id": "17741",
      "quality": "BDRip 720p",
      "camrip": false,
      "blocked_countries": [],
      "blocked_seasons": {},
      "created_at": "2020-01-27T08:44:39Z",
      "updated_at": "2020-01-27T08:44:39Z"
    },
    {
      "id": "serial-21784",
      "type": "anime-serial",
      "link": "",
      "title": "Служащий x Служба",
      "title_orig": "Servant X Service",
      "other_title": "サーバント×サービス",
      "translation": {
        "id": 767,
        "title": "SHIZA Project",
        "type": "voice"
      },
      "year": 2013,
      "last_season": 1,
      "last_episode": 13,
      "episodes_count": 13,
      "kinopoisk_id": "772924",
      "imdb_id": "tt2904596",
      "worldart_link": "http://www.world-art.ru/animation/animation.php?id=1420",
      "shikimori_id": "18119",
      "quality": "BDRip 720p",
      "camrip": false,
      "blocked_countries": [],
      "blocked_seasons": {},
      "created_at": "2020-01-27T08:42:44Z",
      "updated_at": "2020-01-27T08:42:44Z"
    },
    {
      "id": "serial-21783",
      "type": "anime-serial",
      "link": "",
      "title": "Вольный стиль! [ТВ-1]",
      "title_orig": "Free!",
      "other_title": "Свобода! Бесконечное лето / Вольный!",
      "translation": {
        "id": 767,
        "title": "SHIZA Project",
        "type": "voice"
      },
      "year": 2013,
      "last_season": 1,
      "last_episode": 12,
      "episodes_count": 15,
      "kinopoisk_id": "775162",
      "imdb_id": "tt2904418",
      "worldart_link": "http://www.world-art.ru/animation/animation.php?id=1466",
      "shikimori_id": "18507",
      "quality": "BDRip 720p",
      "camrip": false,
      "blocked_countries": [],
      "blocked_seasons": {},
      "created_at": "2020-01-27T08:39:38Z",
      "updated_at": "2020-01-27T08:39:38Z"
    },
    {
      "id": "serial-21782",
      "type": "anime-serial",
      "link": "",
      "title": "Кровавый парень",
      "title_orig": "Blood Lad",
      "other_title": "ブラッドラッド",
      "translation": {
        "id": 767,
        "title": "SHIZA Project",
        "type": "voice"
      },
      "year": 2013,
      "last_season": 1,
      "last_episode": 10,
      "episodes_count": 10,
      "kinopoisk_id": "747607",
      "imdb_id": "tt2760784",
      "worldart_link": "http://www.world-art.ru/animation/animation.php?id=307",
      "shikimori_id": "11633",
      "quality": "BDRip 720p",
      "camrip": false,
      "blocked_countries": [],
      "blocked_seasons": {},
      "created_at": "2020-01-27T08:30:39Z",
      "updated_at": "2020-01-27T08:30:39Z"
    },
    {
      "id": "serial-21781",
      "type": "anime-serial",
      "link": "",
      "title": "Семейка не от мира сего [ТВ-1]",
      "title_orig": "Uchouten Kazoku",
      "other_title": "Экзотическая семейка",
      "translation": {
        "id": 767,
        "title": "SHIZA Project",
        "type": "voice"
      },
      "year": 2013,
      "last_season": 1,
      "last_episode": 13,
      "episodes_count": 13,
      "kinopoisk_id": "772923",
      "imdb_id": "tt2909936",
      "worldart_link": "http://www.world-art.ru/animation/animation.php?id=1410",
      "shikimori_id": "17909",
      "quality": "BDRip 720p",
      "camrip": false,
      "blocked_countries": [],
      "blocked_seasons": {},
      "created_at": "2020-01-27T08:28:42Z",
      "updated_at": "2020-01-27T08:28:42Z"
    },
    {
      "id": "serial-21780",
      "type": "anime-serial",
      "link": "",
      "title": "Судьба: Девочка-волшебница Иллия [ТВ-1]",
      "title_orig": "Fate/Kaleid Liner Prisma Illya",
      "other_title": "Судьба - Девочка-волшебница Илия",
      "translation": {
        "id": 767,
        "title": "SHIZA Project",
        "type": "voice"
      },
      "year": 2013,
      "last_season": 1,
      "last_episode": 10,
      "episodes_count": 15,
      "kinopoisk_id": "761614",
      "imdb_id": "tt2904426",
      "worldart_link": "http://www.world-art.ru/animation/animation.php?id=860",
      "shikimori_id": "14829",
      "quality": "BDRip 720p",
      "camrip": false,
      "blocked_countries": [],
      "blocked_seasons": {},
      "created_at": "2020-01-27T08:25:46Z",
      "updated_at": "2020-01-27T08:25:46Z"
    },
    {
      "id": "serial-21779",
      "type": "anime-serial",
      "link": "",
      "title": "Пёс и ножницы",
      "title_orig": "Inu to Hasami wa Tsukaiyou",
      "other_title": "Пес и Пускающая в ход ножницы / Пес & Ножницы / Inu to Hasami wa Tsukaiyou",
      "translation": {
        "id": 767,
        "title": "SHIZA Project",
        "type": "voice"
      },
      "year": 2013,
      "last_season": 1,
      "last_episode": 12,
      "episodes_count": 12,
      "kinopoisk_id": "787902",
      "imdb_id": "tt2904570",
      "worldart_link": "http://www.world-art.ru/animation/animation.php?id=1390",
      "shikimori_id": "17831",
      "quality": "BDRip 720p",
      "camrip": false,
      "blocked_countries": [],
      "blocked_seasons": {},
      "created_at": "2020-01-27T08:19:13Z",
      "updated_at": "2020-01-27T08:19:13Z"
    }
  ]
}
